{"generated_at":1685474043088,"log":["820dd1d0016763cda6177104e66e09c8634150be","78883ea57db418857c6ad026d767ccdb86205e40","9cc9b45948432e9b74c4152bf90b7843dc6b26e0","828fa9af113ac3831faedd5b6825f34d678865c9","8a615b27ad30af313882a57ea28fc8d979adfbc7","5184b215a9aff0e4eb52d75e6fa5c5d9a2086859"],"release_logs":{"stable":["820dd1d0016763cda6177104e66e09c8634150be","78883ea57db418857c6ad026d767ccdb86205e40","9cc9b45948432e9b74c4152bf90b7843dc6b26e0","828fa9af113ac3831faedd5b6825f34d678865c9","8a615b27ad30af313882a57ea28fc8d979adfbc7","5184b215a9aff0e4eb52d75e6fa5c5d9a2086859"]},"authors":{"MDQ6VXNlcjQ3MDEzMzg=":{"id":"MDQ6VXNlcjQ3MDEzMzg=","user":"akien-mga","avatar":"https://avatars.githubusercontent.com/u/4701338?u=4a42fd867f2c449fcc23adf635dd574dae98e6c2&v=4","url":"https://github.com/akien-mga","pull_count":0,"commit_count":2},"MDQ6VXNlcjU1OTk3OTY=":{"id":"MDQ6VXNlcjU1OTk3OTY=","user":"vnen","avatar":"https://avatars.githubusercontent.com/u/5599796?u=4609ceaeea06ef2484368f7ecdf0c9262a8dd825&v=4","url":"https://github.com/vnen","pull_count":1,"commit_count":2},"MDQ6VXNlcjYyNjUzMDc=":{"id":"MDQ6VXNlcjYyNjUzMDc=","user":"reduz","avatar":"https://avatars.githubusercontent.com/u/6265307?u=987b9f7a5547e1e9937291fc286ab3f13e9b433c&v=4","url":"https://github.com/reduz","pull_count":0,"commit_count":2},"MDQ6VXNlcjY5OTYxOTE=":{"id":"MDQ6VXNlcjY5OTYxOTE=","user":"leonkrause","avatar":"https://avatars.githubusercontent.com/u/6996191?v=4","url":"https://github.com/leonkrause","pull_count":1,"commit_count":2},"MDQ6VXNlcjk4MDE4MDI=":{"id":"MDQ6VXNlcjk4MDE4MDI=","user":"SuperUserNameMan","avatar":"https://avatars.githubusercontent.com/u/9801802?v=4","url":"https://github.com/SuperUserNameMan","pull_count":1,"commit_count":2}},"commits":{"820dd1d0016763cda6177104e66e09c8634150be":{"hash":"820dd1d0016763cda6177104e66e09c8634150be","is_merge":false,"authored_by":["MDQ6VXNlcjQ3MDEzMzg="],"author_raw":"Rémi Verschelde <rverschelde@gmail.com>","committer_raw":"Rémi Verschelde <rverschelde@gmail.com>","summary":"Version 2.0.4.1, hotfix for #5620","body":"","is_cherrypick":false,"cherrypick_hash":"","pull":""},"78883ea57db418857c6ad026d767ccdb86205e40":{"hash":"78883ea57db418857c6ad026d767ccdb86205e40","is_merge":false,"authored_by":["MDQ6VXNlcjU1OTk3OTY="],"author_raw":"George Marques <george@gmarqu.es>","committer_raw":"Rémi Verschelde <rverschelde@gmail.com>","summary":"Fix builtin OpenSSL configuration","body":"Fixes a bug that happens on Windows 64-bits.\n\n(cherry picked from commit 2c6d0d490519016986c1c5be992ff53fbdea8c8f)","is_cherrypick":true,"cherrypick_hash":"2c6d0d490519016986c1c5be992ff53fbdea8c8f","pull":""},"2c6d0d490519016986c1c5be992ff53fbdea8c8f":{"hash":"2c6d0d490519016986c1c5be992ff53fbdea8c8f","is_merge":false,"authored_by":["MDQ6VXNlcjU1OTk3OTY="],"author_raw":"George Marques <george@gmarqu.es>","committer_raw":"George Marques <george@gmarqu.es>","summary":"Fix builtin OpenSSL configuration","body":"Fixes a bug that happens on Windows 64-bits.","is_cherrypick":false,"cherrypick_hash":"","pull":5618},"9cc9b45948432e9b74c4152bf90b7843dc6b26e0":{"hash":"9cc9b45948432e9b74c4152bf90b7843dc6b26e0","is_merge":false,"authored_by":["MDQ6VXNlcjYyNjUzMDc="],"author_raw":"Juan Linietsky <reduzio@gmail.com>","committer_raw":"Rémi Verschelde <rverschelde@gmail.com>","summary":"Finally fixes the infamous bug #4444, hoping to never see you again.","body":"Closes #4444.\n\n(cherry picked from commit b0f0ae072367b061e4ff59b17b920f2d67b41e3a)","is_cherrypick":true,"cherrypick_hash":"b0f0ae072367b061e4ff59b17b920f2d67b41e3a","pull":""},"b0f0ae072367b061e4ff59b17b920f2d67b41e3a":{"hash":"b0f0ae072367b061e4ff59b17b920f2d67b41e3a","is_merge":false,"authored_by":["MDQ6VXNlcjYyNjUzMDc="],"author_raw":"Juan Linietsky <reduzio@gmail.com>","committer_raw":"Juan Linietsky <reduzio@gmail.com>","summary":"Finally fixes the infamous bug #4444, hoping to never see you again.","body":"Closes #4444.","is_cherrypick":false,"cherrypick_hash":"","pull":""},"828fa9af113ac3831faedd5b6825f34d678865c9":{"hash":"828fa9af113ac3831faedd5b6825f34d678865c9","is_merge":false,"authored_by":["MDQ6VXNlcjY5OTYxOTE="],"author_raw":"eska <eska@eska.me>","committer_raw":"Rémi Verschelde <rverschelde@gmail.com>","summary":"Fix help search dialog titles","body":"(cherry picked from commit af395cea42913f8f9d12912d7eee9011dd557ec7)","is_cherrypick":true,"cherrypick_hash":"af395cea42913f8f9d12912d7eee9011dd557ec7","pull":""},"af395cea42913f8f9d12912d7eee9011dd557ec7":{"hash":"af395cea42913f8f9d12912d7eee9011dd557ec7","is_merge":false,"authored_by":["MDQ6VXNlcjY5OTYxOTE="],"author_raw":"eska <eska@eska.me>","committer_raw":"eska <eska@eska.me>","summary":"Fix help search dialog titles","body":"","is_cherrypick":false,"cherrypick_hash":"","pull":5609},"8a615b27ad30af313882a57ea28fc8d979adfbc7":{"hash":"8a615b27ad30af313882a57ea28fc8d979adfbc7","is_merge":false,"authored_by":["MDQ6VXNlcjk4MDE4MDI="],"author_raw":"SuperUserNameMan <yoann@terminajones.com>","committer_raw":"Rémi Verschelde <rverschelde@gmail.com>","summary":"fixes #5464 windows_joystick close_joystick bug","body":"(cherry picked from commit 2511f48339ab9fa489cf31e7c985547ddb69ae4e)","is_cherrypick":true,"cherrypick_hash":"2511f48339ab9fa489cf31e7c985547ddb69ae4e","pull":""},"2511f48339ab9fa489cf31e7c985547ddb69ae4e":{"hash":"2511f48339ab9fa489cf31e7c985547ddb69ae4e","is_merge":false,"authored_by":["MDQ6VXNlcjk4MDE4MDI="],"author_raw":"SuperUserNameMan <yoann@terminajones.com>","committer_raw":"SuperUserNameMan <yoann@terminajones.com>","summary":"fixes #5464 windows_joystick close_joystick bug","body":"","is_cherrypick":false,"cherrypick_hash":"","pull":5495},"5184b215a9aff0e4eb52d75e6fa5c5d9a2086859":{"hash":"5184b215a9aff0e4eb52d75e6fa5c5d9a2086859","is_merge":false,"authored_by":["MDQ6VXNlcjQ3MDEzMzg="],"author_raw":"Rémi Verschelde <rverschelde@gmail.com>","committer_raw":"Rémi Verschelde <rverschelde@gmail.com>","summary":"Revert \"update EditorDirDialog on external change, closes #4629\"","body":"This reverts commit 257d3706777bed2f07003f53435144f48707d020.\nFixes #5620.","is_cherrypick":false,"cherrypick_hash":"","pull":""}},"pulls":{"5495":{"id":"MDExOlB1bGxSZXF1ZXN0NzU3MjEwMTU=","public_id":5495,"url":"https://github.com/godotengine/godot/pull/5495","diff_url":"https://github.com/godotengine/godot/pull/5495.diff","patch_url":"https://github.com/godotengine/godot/pull/5495.patch","title":"fixes #5464 windows_joystick close_joystick bug","state":"MERGED","is_draft":false,"authored_by":"MDQ6VXNlcjk4MDE4MDI=","created_at":"2016-06-29T21:03:14Z","updated_at":"2016-07-09T14:34:00Z","target_branch":"master","labels":[{"id":"MDU6TGFiZWw3MzMzMDA2NA==","name":"bug","color":"#ff6055"},{"id":"MDU6TGFiZWwyMDU0MTc0MTM=","name":"platform:windows","color":"#e4e4e4"},{"id":"MDU6TGFiZWwyNzkwOTc5NjY=","name":"topic:core","color":"#ffee88"}],"commits":["2511f48339ab9fa489cf31e7c985547ddb69ae4e"],"group_key":"core","group_name":"Core"},"5609":{"id":"MDExOlB1bGxSZXF1ZXN0NzY4NDkyOTg=","public_id":5609,"url":"https://github.com/godotengine/godot/pull/5609","diff_url":"https://github.com/godotengine/godot/pull/5609.diff","patch_url":"https://github.com/godotengine/godot/pull/5609.patch","title":"Fix help search dialog titles","state":"MERGED","is_draft":false,"authored_by":"MDQ6VXNlcjY5OTYxOTE=","created_at":"2016-07-09T15:26:01Z","updated_at":"2016-07-13T13:45:07Z","target_branch":"master","labels":[{"id":"MDU6TGFiZWw3MzMzMDA2NA==","name":"bug","color":"#ff6055"},{"id":"MDU6TGFiZWwyNzkwOTgyMTk=","name":"topic:editor","color":"#ffee88"},{"id":"MDU6TGFiZWwyODM1MTg3MzM=","name":"usability","color":"#447744"}],"commits":["af395cea42913f8f9d12912d7eee9011dd557ec7"],"group_key":"editor","group_name":"Editor"},"5618":{"id":"MDExOlB1bGxSZXF1ZXN0NzY4NTk1OTI=","public_id":5618,"url":"https://github.com/godotengine/godot/pull/5618","diff_url":"https://github.com/godotengine/godot/pull/5618.diff","patch_url":"https://github.com/godotengine/godot/pull/5618.patch","title":"Fix builtin OpenSSL configuration","state":"MERGED","is_draft":false,"authored_by":"MDQ6VXNlcjU1OTk3OTY=","created_at":"2016-07-09T23:16:13Z","updated_at":"2016-07-10T14:44:07Z","target_branch":"master","labels":[{"id":"MDU6TGFiZWw3MzMzMDA2NA==","name":"bug","color":"#ff6055"},{"id":"MDU6TGFiZWwyMDU0MTc0MTM=","name":"platform:windows","color":"#e4e4e4"},{"id":"MDU6TGFiZWwzNzA0NzE3OTU=","name":"topic:thirdparty","color":"#ffee88"}],"commits":["2c6d0d490519016986c1c5be992ff53fbdea8c8f"],"group_key":"thirdparty","group_name":"Thirdparty"}}}